oslo_utils/__init__.py
oslo_utils/_i18n.py
oslo_utils/dictutils.py
oslo_utils/encodeutils.py
oslo_utils/eventletutils.py
oslo_utils/excutils.py
oslo_utils/fileutils.py
oslo_utils/fixture.py
oslo_utils/importutils.py
oslo_utils/netutils.py
oslo_utils/reflection.py
oslo_utils/secretutils.py
oslo_utils/specs_matcher.py
oslo_utils/strutils.py
oslo_utils/timeutils.py
oslo_utils/units.py
oslo_utils/uuidutils.py
oslo_utils/version.py
oslo_utils/versionutils.py
oslo_utils/imageutils/__init__.py
oslo_utils/imageutils/__main__.py
oslo_utils/imageutils/cli.py
oslo_utils/imageutils/format_inspector.py
oslo_utils/imageutils/qemu.py
oslo_utils/locale/de/LC_MESSAGES/oslo_utils.po
oslo_utils/locale/en_GB/LC_MESSAGES/oslo_utils.po
oslo_utils/locale/fr/LC_MESSAGES/oslo_utils.po
oslo_utils/locale/ka_GE/LC_MESSAGES/oslo_utils.po
oslo_utils/tests/__init__.py
oslo_utils/tests/base.py
oslo_utils/tests/test_dictutils.py
oslo_utils/tests/test_eventletutils.py
oslo_utils/tests/test_excutils.py
oslo_utils/tests/test_fileutils.py
oslo_utils/tests/test_fixture.py
oslo_utils/tests/test_importutils.py
oslo_utils/tests/test_netutils.py
oslo_utils/tests/test_reflection.py
oslo_utils/tests/test_secretutils.py
oslo_utils/tests/test_specs_matcher.py
oslo_utils/tests/test_strutils.py
oslo_utils/tests/test_timeutils.py
oslo_utils/tests/test_uuidutils.py
oslo_utils/tests/test_versionutils.py
oslo_utils/tests/tests_encodeutils.py
oslo_utils/tests/fake/__init__.py
oslo_utils/tests/fake/v2/__init__.py
oslo_utils/tests/fake/v2/dummpy.py
oslo_utils/tests/imageutils/__init__.py
oslo_utils/tests/imageutils/test_format_inspector.py
oslo_utils/tests/imageutils/test_qemu.py
oslo_utils-9.0.0.dist-info/AUTHORS
oslo_utils-9.0.0.dist-info/LICENSE
oslo_utils-9.0.0.dist-info/METADATA
oslo_utils-9.0.0.dist-info/WHEEL
oslo_utils-9.0.0.dist-info/pbr.json
oslo_utils-9.0.0.dist-info/top_level.txt
oslo_utils-9.0.0.dist-info/RECORD
