Metadata-Version: 2.1
Name: oslo.utils
Version: 9.0.0
Summary: Oslo Utility library
Home-page: https://docs.openstack.org/oslo.utils/latest/
Author: OpenStack
Author-email: openstack-discuss@lists.openstack.org
Classifier: Environment :: OpenStack
Classifier: Intended Audience :: Information Technology
Classifier: Intended Audience :: System Administrators
Classifier: License :: OSI Approved :: Apache Software License
Classifier: Operating System :: POSIX :: Linux
Classifier: Programming Language :: Python
Classifier: Programming Language :: Python :: 3
Classifier: Programming Language :: Python :: 3.9
Classifier: Programming Language :: Python :: 3.10
Classifier: Programming Language :: Python :: 3.11
Classifier: Programming Language :: Python :: 3.12
Classifier: Programming Language :: Python :: 3 :: Only
Classifier: Programming Language :: Python :: Implementation :: CPython
Requires-Python: >=3.9
License-File: LICENSE
Requires-Dist: iso8601>=0.1.11
Requires-Dist: oslo.i18n>=3.15.3
Requires-Dist: netaddr>=0.10.0
Requires-Dist: debtcollector>=1.2.0
Requires-Dist: pyparsing>=2.1.0
Requires-Dist: packaging>=20.4
Requires-Dist: tzdata>=2022.4
Requires-Dist: PyYAML>=3.13
Requires-Dist: psutil>=3.2.2
Requires-Dist: pbr>=6.1.0
